<?xml version="1.0" encoding="utf-8"?>
<!DOCTYPE world []>
<world>
    <head>
    </head>
    <body>
        <room id="room1" enterable="true">
            <object>
                <face>
                    <p>This is the appearance of the object.</p>
                    <img src="image.png" />
                </face>
                <body>
                </body>
            </object>
            <object aspect="opaque">
                <face>Object example - transparency</face>
                <body>
                    <object>
                        <face>I'm hidden because my container is opaque!</face>
                    </object>
                </body>
            </object>
        </room>
        <room id="room2" enterable="true">
        </room>
    </body>
</world>